libroadrunner-2.9.0.dist-info/licenses/AUTHORS.txt
libroadrunner-2.9.0.dist-info/licenses/LICENSE.txt
libroadrunner-2.9.0.dist-info/licenses/NOTICE.txt
roadrunner/__init__.py
roadrunner/_roadrunner.so
roadrunner/roadrunner.py
roadrunner/stochastic/__init__.py
roadrunner/stochastic/ensemble.py
roadrunner/tests/EcoliCore.xml
roadrunner/tests/README.txt
roadrunner/tests/RoadRunnerTest.py
roadrunner/tests/SBMLTest.py
roadrunner/tests/SettingTestsSwigAPI.py
roadrunner/tests/TestModelFactory.py
roadrunner/tests/_SettingTestsSwigAPI.so
roadrunner/tests/_TestModelFactory.so
roadrunner/tests/__init__.py
roadrunner/tests/__main__.py
roadrunner/tests/_picklable_swig.so
roadrunner/tests/download_biomodels.py
roadrunner/tests/feedback.xml
roadrunner/tests/linearPathwayClosed.xml
roadrunner/tests/linearPathwayOpen.xml
roadrunner/tests/picklable_swig.py
roadrunner/tests/test_1.xml
roadrunner/tests/test_auto_plugin.py
roadrunner/tests/test_automaticMoietyConservationAnalysis.py
roadrunner/tests/test_forwardSensitivitySolver.py
roadrunner/tests/test_integrator.py
roadrunner/tests/test_jacobian.py
roadrunner/tests/test_namedArray.py
roadrunner/tests/test_pickle.py
roadrunner/tests/test_python_api.py
roadrunner/tests/test_roadrunner_map.py
roadrunner/tests/test_rrtests.py
roadrunner/tests/test_runStochasticTestSuite.py
roadrunner/tests/test_settings.py
roadrunner/tests/test_steadyStateSolver.py
roadrunner/tests/test_structuralAnalysis.py
roadrunner/tests/test_testModelFactory.py
roadrunner/tests/testfiles.py
roadrunner/tests/test_data/Absolute_Tolerance1.rrtest
roadrunner/tests/test_data/Add_Event_Assignment1.rrtest
roadrunner/tests/test_data/Add_Reactions1.rrtest
roadrunner/tests/test_data/Add_Reactions2.rrtest
roadrunner/tests/test_data/Add_Species1.rrtest
roadrunner/tests/test_data/Bimolecular_end.rrtest
roadrunner/tests/test_data/Comp.rrtest
roadrunner/tests/test_data/Conserved_Cycle.rrtest
roadrunner/tests/test_data/Conserved_Cycle_and_Branch.rrtest
roadrunner/tests/test_data/Cycle.rrtest
roadrunner/tests/test_data/Cycle_across_branches.rrtest
roadrunner/tests/test_data/Cycle_to_Input_and_Branch.rrtest
libroadrunner-2.9.0.dist-info/METADATA
libroadrunner-2.9.0.dist-info/WHEEL
libroadrunner-2.9.0.dist-info/top_level.txt
libroadrunner-2.9.0.dist-info/RECORD
