Metadata-Version: 2.4
Name: libroadrunner
Version: 2.9.0
Summary: libRoadRunner: A simulation and analysis library for SBML
Home-page: http://libroadrunner.org
Author: Andy Somogyi, J Kyle Medley, Lucian Smith, Ciaran Welsh, Herbert Sauro
Author-email: tellurium-discuss@u.washington.edu
Classifier: Intended Audience :: Science/Research
Classifier: Operating System :: MacOS :: MacOS X
Classifier: Operating System :: Microsoft :: Windows
Classifier: Operating System :: POSIX
Classifier: Programming Language :: C++
License-File: LICENSE.txt
License-File: NOTICE.txt
License-File: AUTHORS.txt
Requires-Dist: numpy~=2.2
Dynamic: author
Dynamic: author-email
Dynamic: classifier
Dynamic: description
Dynamic: description-content-type
Dynamic: home-page
Dynamic: license-file
Dynamic: requires-dist
Dynamic: summary
